htl/__init__.py
htl/htl.py
tests/__init__.py
tests/test_htl.py
htl-1.0.0.dist-info/LICENSE
htl-1.0.0.dist-info/METADATA
htl-1.0.0.dist-info/WHEEL
htl-1.0.0.dist-info/top_level.txt
htl-1.0.0.dist-info/RECORD
