Metadata-Version: 2.1
Name: htl
Version: 1.0.0
Summary: Library for transform data structures
Home-page: https://github.com/EkaterinaSidorenko17/htl
Author: Sidorenko Ekaterina
Author-email: sidorenkoekaterina01@icloud.com
License: UNKNOWN
Platform: any
Requires-Python: >=3.7
